easyst/__init__.py
easyst-0.0.1.dist-info/licenses/LICENSE
easyst-0.0.1.dist-info/METADATA
easyst-0.0.1.dist-info/WHEEL
easyst-0.0.1.dist-info/top_level.txt
easyst-0.0.1.dist-info/RECORD
