Metadata-Version: 2.4
Name: easyst
Version: 0.0.1
Summary: A small package for easy streamlit app
Author-email: Xiaonan Zhao <zhaoxxn@gmail.com>
Classifier: Programming Language :: Python :: 3
Classifier: License :: OSI Approved :: MIT License
Classifier: Operating System :: OS Independent
Requires-Python: >=3.7
License-File: LICENSE
Requires-Dist: streamlit
Dynamic: license-file
